{"_invocation_id": "3ee3593a-1684-4de7-ad9f-ade90ce64810", "linked": {"0": {"name": "model.raysearch_project.stg_currency_exchange", "type": "model", "succ": [31]}, "1": {"name": "seed.raysearch_project.currency_exchange", "type": "seed", "succ": [0, 18, 20, 21, 22]}, "2": {"name": "model.raysearch_project.stg_customer", "type": "model", "succ": [23]}, "3": {"name": "seed.raysearch_project.customer", "type": "seed", "succ": [2, 6, 7, 8, 9, 10, 11, 12, 14]}, "4": {"name": "model.raysearch_project.stg_transaction", "type": "model", "succ": [28, 29, 30, 32, 36]}, "5": {"name": "seed.raysearch_project.transaction", "type": "seed", "succ": [4, 13, 14, 15, 16, 17, 18, 19]}, "6": {"name": "snapshot.raysearch_project.customer_snapshot", "type": "snapshot"}, "7": {"name": "test.raysearch_project.not_null_customer_customerID.cdb9e51021", "type": "test"}, "8": {"name": "test.raysearch_project.accepted_values_customer_state__VALIDATED__SIGNUP__INACTIVE.e1ca1269bb", "type": "test"}, "9": {"name": "test.raysearch_project.accepted_values_customer_VIP__0__1.93c0b14773", "type": "test"}, "10": {"name": "test.raysearch_project.accepted_values_customer_KYC__0__1.7db04dbc5c", "type": "test"}, "11": {"name": "test.raysearch_project.accepted_values_customer_wantsNewsletter__0__1.d2b7998b41", "type": "test"}, "12": {"name": "test.raysearch_project.not_null_customer_latestUpdate.b0d9ffd70b", "type": "test"}, "13": {"name": "test.raysearch_project.not_null_transaction_customerId.63105569e2", "type": "test"}, "14": {"name": "test.raysearch_project.relationships_transaction_customerId__customerID__ref_customer_.07ef3b4fe8", "type": "test"}, "15": {"name": "test.raysearch_project.not_null_transaction_amount.8ca6f973e6", "type": "test"}, "16": {"name": "test.raysearch_project.accepted_values_transaction_txType__DEPOSIT__WITHDRAWAL.005c6de30a", "type": "test"}, "17": {"name": "test.raysearch_project.not_null_transaction_txCurrency.7798fc4041", "type": "test"}, "18": {"name": "test.raysearch_project.relationships_transaction_txCurrency__currency__ref_currency_exchange_.b837e7b506", "type": "test"}, "19": {"name": "test.raysearch_project.not_null_transaction_date.8d1d66da2c", "type": "test"}, "20": {"name": "test.raysearch_project.not_null_currency_exchange_date.f508e913b3", "type": "test"}, "21": {"name": "test.raysearch_project.not_null_currency_exchange_currency.3314a18e4f", "type": "test"}, "22": {"name": "test.raysearch_project.not_null_currency_exchange_baseRateEuro.f405e79eff", "type": "test"}, "23": {"name": "model.raysearch_project.trf_customer_scd2", "type": "model", "succ": [24, 25, 26, 27, 28, 29, 36]}, "24": {"name": "test.raysearch_project.not_null_trf_customer_scd2_customer_id.7602333dfb", "type": "test"}, "25": {"name": "test.raysearch_project.not_null_trf_customer_scd2_etl_valid_from.2333e40f94", "type": "test"}, "26": {"name": "test.raysearch_project.not_null_trf_customer_scd2_is_current.59a6a18595", "type": "test"}, "27": {"name": "test.raysearch_project.dbt_utils_unique_combination_of_columns_trf_customer_scd2_customer_id__etl_valid_from.90b4e97f49", "type": "test"}, "28": {"name": "model.raysearch_project.trf_transaction_customer_on_day", "type": "model"}, "29": {"name": "test.raysearch_project.trf_transaction_customer_on_day", "type": "test"}, "30": {"name": "model.raysearch_project.trf_transaction_exchange_on_day", "type": "model"}, "31": {"name": "model.raysearch_project.trf_currency_exchange", "type": "model", "succ": [30, 32, 33, 34, 35, 36]}, "32": {"name": "test.raysearch_project.trf_transaction_exchange_on_day", "type": "test"}, "33": {"name": "test.raysearch_project.not_null_trf_currency_exchange_rate_date.e5151cbcc2", "type": "test"}, "34": {"name": "test.raysearch_project.not_null_trf_currency_exchange_currency_code.753af6a7de", "type": "test"}, "35": {"name": "test.raysearch_project.dbt_utils_unique_combination_of_columns_trf_currency_exchange_rate_date__currency_code.225df91bc9", "type": "test"}, "36": {"name": "model.raysearch_project.trf_transaction", "type": "model", "succ": [37, 38, 39, 40, 41]}, "37": {"name": "test.raysearch_project.not_null_trf_transaction_transaction_date.645dbc8e37", "type": "test"}, "38": {"name": "test.raysearch_project.not_null_trf_transaction_customer_id.a1a6396f73", "type": "test"}, "39": {"name": "test.raysearch_project.not_null_trf_transaction_country_code.6e598f518b", "type": "test"}, "40": {"name": "test.raysearch_project.not_null_trf_transaction_account_type.0785bb4951", "type": "test"}, "41": {"name": "test.raysearch_project.dbt_utils_unique_combination_of_columns_trf_transaction_transaction_date__customer_id__country_code__account_type.a655f84d78", "type": "test"}}}